hlem_framework/__init__.py
hlem_framework/component.py
hlem_framework/correlation.py
hlem_framework/feature_eval.py
hlem_framework/frames.py
hlem_framework/hl_log.py
hlem_framework/hle_generation.py
hlem_framework/hlem.py
hlem_framework/linkage.py
hlem_framework/main.py
hlem_framework/preprocess.py
hlem_framework-0.0.2.dist-info/METADATA
hlem_framework-0.0.2.dist-info/WHEEL
hlem_framework-0.0.2.dist-info/top_level.txt
hlem_framework-0.0.2.dist-info/RECORD
