Metadata-Version: 2.1
Name: hlem-framework
Version: 0.0.2
Summary: A Process Mining Framework for High-Level Event Mining
Author-email: Bianka Bakullari <bianka.bakullari@pads.rwth-aachen.de>
Project-URL: Homepage, https://github.com/biankabakullari/hlem-framework
Project-URL: Bug Tracker, https://github.com/biankabakullari/hlem-framework/issues
Classifier: Programming Language :: Python :: 3
Classifier: License :: OSI Approved :: MIT License
Classifier: Operating System :: OS Independent
Requires-Python: >=3.7
Requires-Dist: pm4py (==2.2.32)
Requires-Dist: networkx
Requires-Dist: pandas
Requires-Dist: numpy
